<NotepadPlus>
    <UserLang name="F#" ext="fs">
        <Settings>
            <Global caseIgnored="no" />
            <TreatAsSymbol comment="no" commentLine="no" />
            <Prefix words1="no" words2="no" words3="no" words4="no" />
        </Settings>
        <KeywordLists>
            <Keywords name="Delimiters">&quot;00&quot;00</Keywords>
            <Keywords name="Folder+"></Keywords>
            <Keywords name="Folder-"></Keywords>
            <Keywords name="Operators">- % ( ) * . : ; [ ] | + &lt; = &gt;</Keywords>
            <Keywords name="Comment">1(* 2*) 0// 0///</Keywords>
            <Keywords name="Words1">abstract and as assert base begin class default delegate do done downcast downto elif else end exception extern false finally for fun function if in inherit inline interface internal lazy let match member module mutable namespace new not null of open or override private public rec return static struct then to true try type upcast use val void when while with yield</Keywords>
            <Keywords name="Words2">asr land lor lsl lsr lxor mod sig</Keywords>
            <Keywords name="Words3">atomic break checked component const constraint constructor continue eager event external fixed functor global include method mixin object parallel process protected pure sealed tailcall trait virtual volatile</Keywords>
            <Keywords name="Words4">bool byte sbyte int16 uint16 int uint int64 uint64 char string decimal unit void</Keywords>
        </KeywordLists>
        <Styles>
            <WordsStyle name="DEFAULT" styleID="11" fgColor="000000" bgColor="FFFFFF" fontName="" fontStyle="0" />
            <WordsStyle name="FOLDEROPEN" styleID="12" fgColor="000000" bgColor="FFFFFF" fontName="" fontStyle="0" />
            <WordsStyle name="FOLDERCLOSE" styleID="13" fgColor="000000" bgColor="FFFFFF" fontName="" fontStyle="0" />
            <WordsStyle name="KEYWORD1" styleID="5" fgColor="0000FF" bgColor="FFFFFF" fontName="" fontStyle="0" />
            <WordsStyle name="KEYWORD2" styleID="6" fgColor="0000FF" bgColor="FFFFFF" fontName="" fontStyle="0" />
            <WordsStyle name="KEYWORD3" styleID="7" fgColor="0000FF" bgColor="FFFFFF" fontName="" fontStyle="0" />
            <WordsStyle name="KEYWORD4" styleID="8" fgColor="8000FF" bgColor="FFFFFF" fontName="" fontStyle="0" />
            <WordsStyle name="COMMENT" styleID="1" fgColor="008000" bgColor="FFFFFF" fontName="" fontStyle="2" />
            <WordsStyle name="COMMENT LINE" styleID="2" fgColor="008000" bgColor="FFFFFF" fontName="" fontStyle="2" />
            <WordsStyle name="NUMBER" styleID="4" fgColor="FF8000" bgColor="FFFFFF" fontName="" fontStyle="0" />
            <WordsStyle name="OPERATOR" styleID="10" fgColor="000080" bgColor="FFFFFF" fontName="" fontStyle="0" />
            <WordsStyle name="DELIMINER1" styleID="14" fgColor="C0C0C0" bgColor="FFFFFF" fontName="" fontStyle="0" />
            <WordsStyle name="DELIMINER2" styleID="15" fgColor="000000" bgColor="FFFFFF" fontName="" fontStyle="0" />
            <WordsStyle name="DELIMINER3" styleID="16" fgColor="000000" bgColor="FFFFFF" fontName="" fontStyle="0" />
        </Styles>
    </UserLang>
</NotepadPlus>
